mosaik_components/timescaledb/__init__.py
mosaik_components/timescaledb/custom_writer.py
mosaik_components/timescaledb/multi_writer.py
mosaik_components/timescaledb/single_writer.py
mosaik_components/timescaledb/writer.py
mosaik_timescaledb-0.1.1.dist-info/LICENSE
mosaik_timescaledb-0.1.1.dist-info/METADATA
mosaik_timescaledb-0.1.1.dist-info/WHEEL
mosaik_timescaledb-0.1.1.dist-info/RECORD
