Metadata-Version: 2.1
Name: mosaik-timescaledb
Version: 0.1.1
Summary: A data collector for mosaik using timescaledb
Author: Alexandro Steinert
Author-email: alexandro.steinert@offis.de
Requires-Python: >=3.8,<4.0
Classifier: Programming Language :: Python :: 3
Classifier: Programming Language :: Python :: 3.8
Classifier: Programming Language :: Python :: 3.9
Classifier: Programming Language :: Python :: 3.10
Classifier: Programming Language :: Python :: 3.11
Classifier: Programming Language :: Python :: 3.12
Requires-Dist: mosaik-api-v3 (>=3.0.4,<4.0.0)
Requires-Dist: pgcopy (>=1.5.0,<2.0.0)
Requires-Dist: psycopg2 (>=2.9.7,<3.0.0)
